insertcode/__init__.py
insertcode/__main__.py
insertcode-0.0.2.dist-info/METADATA
insertcode-0.0.2.dist-info/RECORD
insertcode-0.0.2.dist-info/WHEEL
insertcode-0.0.2.dist-info/top_level.txt
insertcode-0.0.2.dist-info/zip-safe
