Metadata-Version: 2.1
Name: insertcode
Version: 0.0.2
Summary: extension util for insert different code in the different file type
Home-page: http://github.com/jeppeter/insertcode
Author: jeppeter Wang
Author-email: jeppeter@gmail.com
License: MIT
Platform: UNKNOWN
Classifier: Programming Language :: Python
Classifier: License :: OSI Approved :: MIT License
Classifier: Operating System :: OS Independent
Requires-Dist: extargsparse
